placaplaca/Placas.py
placaplaca/__init__.py
PlacaPlaca-1.7.dist-info/LICENSE
PlacaPlaca-1.7.dist-info/METADATA
PlacaPlaca-1.7.dist-info/WHEEL
PlacaPlaca-1.7.dist-info/top_level.txt
PlacaPlaca-1.7.dist-info/RECORD
