Metadata-Version: 2.1
Name: PlacaPlaca
Version: 1.7
Summary: Identificador de placas de Panama
Home-page: https://github.com/VvLuijovV/Placas
Author: Luijo
Author-email: luijo0319@gmail.com
License: UNKNOWN
Platform: UNKNOWN
Classifier: Programming Language :: Python :: 3
Classifier: License :: OSI Approved :: MIT License
Classifier: Operating System :: OS Independent
